{
    "class": "DepictionTabView",
    "headerImage": "https://invalidunit.github.io/sileodepiction/Default/top.png",
    "tintColor": "#FF4455",
    "minVersion": "0.3",
    "tabs": [
        {
            "class": "DepictionStackView",
            "tabname": "描述",
            "views": [
                {
                    "title":"跳转 AppStore 安装 Bark",
                    "action":"https://apps.apple.com/app/id1403753865",
                    "class":"DepictionTableButtonView"
                },
                {
                    "class": "DepictionSpacerView",
                    "spacing": 1
                },
                {
                    "class": "DepictionSeparatorView"
                },
                {
                    "class": "DepictionSpacerView",
                    "spacing": 1
                },
                {
                    "class": "DepictionMarkdownView",
                    "markdown": "检查 AppStore 中软件变更然后使用 bark 推送变更通知的守护进程，每 1 小时由 launch 拉起来检测一次变更，其他时间完全没启动，主要自用",
                    "useRawFormat": true
                },
                {
                    "class": "DepictionMarkdownView",
                    "markdown": "配置完 key 后可以重装此包来马上开始工作，首次使用将会推送一个 Hello World 的通知来提醒你已经开始工作了",
                    "useRawFormat": true
                },
                {
                    "class": "DepictionMarkdownView",
                    "markdown": "可点击下方来查看怎么配置 cac",
                    "useRawFormat": true
                },
                {
                    "title":"查看 cac 配置说明",
                    "action":"https://invalidunit.github.io/sileodepiction/com.nan.cac/html/cac.html",
                    "class":"DepictionTableButtonView"
                },
                {
                    "class": "DepictionScreenshotsView",
                    "itemCornerRadius": 6,
                    "itemSize": "{160, 346.4533333333333}",
                    "screenshots": [
                        {
                            "accessibilityText": "Screenshot",
                            "url": "https://invalidunit.github.io/sileodepiction/com.nan.cac/Screenshot_01.png"
                        },
                        {
                            "accessibilityText": "Screenshot",
                            "url": "https://invalidunit.github.io/sileodepiction/com.nan.cac/Screenshot_02.png"
                        },
                        {
                            "accessibilityText": "Screenshot",
                            "url": "https://invalidunit.github.io/sileodepiction/com.nan.cac/Screenshot_03.png"
                        }
                    ]
                },
                {
                    "class": "DepictionSpacerView",
                    "spacing": 16
                },
                {
                    "class": "DepictionSeparatorView"
                },
                {
                    "class": "DepictionSpacerView",
                    "spacing": 16
                },
                {
                    "class": "DepictionHeaderView",
                    "title": "详情",
                    "useBoldText": true,
                    "useBottomMargin": false
                },
                {
                    "class": "DepictionSpacerView",
                    "spacing": 8
                },
                {
                    "class": "DepictionTableTextView",
                    "text": "zhaonan",
                    "title": "作者"
                },
                {
                    "class": "DepictionTableTextView",
                    "text": "0.1.0",
                    "title": "最新版本"
                },
                {
                    "class": "DepictionTableTextView",
                    "text": "12.0 - 15.9",
                    "title": "支持系统范围"
                },
                {
                    "class": "DepictionTableTextView",
                    "text": "2024 年 01 月 01 日",
                    "title": "最后更新日期"
                },
                {
                    "class": "DepictionSpacerView",
                    "spacing": 16
                }
            ]
        },
        {
            "class": "DepictionStackView",
            "tabname": "更新日志",
            "views": [
                {
                    "class": "DepictionSubheaderView",
                    "title": "0.1.0",
                    "useBoldText": true,
                    "useBottomMargin": false
                },
                {
                    "class": "DepictionMarkdownView",
                    "markdown": "初始版本，初始大屎山。",
                    "useRawFormat": true
                }
            ]
        }
    ],
}